mi_pimento-1.0.2.dist-info/licenses/LICENSE
pimento/pimento_cli.py
pimento/bin/are_there_primers.py
pimento/bin/choose_primer_cutoff.py
pimento/bin/find_cutoffs.py
pimento/bin/generate_bcv.py
pimento/bin/pimento_utils.py
pimento/bin/regex_ambiguous_bases.py
pimento/bin/standard_primer_matching.py
pimento/bin/thresholds.py
pimento/standard_primers/18S.fasta
pimento/standard_primers/26S.fasta
pimento/standard_primers/Arch16S.fasta
pimento/standard_primers/ITS.fasta
pimento/standard_primers/V1-V2.fasta
pimento/standard_primers/V1-V3.fasta
pimento/standard_primers/V1-V9.fasta
pimento/standard_primers/V3-V4.fasta
pimento/standard_primers/V3-V5.fasta
pimento/standard_primers/V3.fasta
pimento/standard_primers/V4-V5.fasta
pimento/standard_primers/V4.fasta
pimento/standard_primers/V5-V6.fasta
pimento/standard_primers/V5-V7.fasta
pimento/standard_primers/V6-V8.fasta
pimento/standard_primers/V6-V9.fasta
pimento/standard_primers/V6.fasta
pimento/standard_primers/V7-V9.fasta
mi_pimento-1.0.2.dist-info/METADATA
mi_pimento-1.0.2.dist-info/WHEEL
mi_pimento-1.0.2.dist-info/entry_points.txt
mi_pimento-1.0.2.dist-info/top_level.txt
mi_pimento-1.0.2.dist-info/RECORD
