Metadata-Version: 2.4
Name: mi-pimento
Version: 1.0.2
Summary: A PrIMEr infereNce TOolkit to facilitate large-scale calling of metabarcoding amplicon sequence variants
Author-email: MGnify team <metagenomics-help@ebi.ac.uk>
License: Apache Software License 2.0
Keywords: bioinformatics,pipelines,metagenomics,primers,reads,sequencing
Classifier: Programming Language :: Python :: 3
Classifier: License :: OSI Approved :: Apache Software License
Classifier: Operating System :: OS Independent
Requires-Python: >=3.10
License-File: LICENSE
Requires-Dist: biopython==1.82
Requires-Dist: numpy==1.26.0
Requires-Dist: pandas==2.0.2
Requires-Dist: regex==2023.12.25
Requires-Dist: click==8.1.7
Requires-Dist: pyfastx>=2.2.0
Requires-Dist: rich==13.9.4
Provides-Extra: tests
Requires-Dist: pytest==7.4.0; extra == "tests"
Requires-Dist: pytest-md==0.2.0; extra == "tests"
Requires-Dist: pytest-workflow==2.0.1; extra == "tests"
Requires-Dist: biopython==1.82; extra == "tests"
Requires-Dist: pandas==2.0.2; extra == "tests"
Requires-Dist: numpy==1.26.0; extra == "tests"
Requires-Dist: regex==2023.12.25; extra == "tests"
Requires-Dist: click==8.1.7; extra == "tests"
Requires-Dist: pyfastx>=2.2.0; extra == "tests"
Requires-Dist: rich==13.9.4; extra == "tests"
Provides-Extra: dev
Requires-Dist: mi-pimento[tests]; extra == "dev"
Requires-Dist: pre-commit==3.8.0; extra == "dev"
Requires-Dist: black==24.8.0; extra == "dev"
Requires-Dist: flake8==7.1.1; extra == "dev"
Requires-Dist: pep8-naming==0.14.1; extra == "dev"
Dynamic: license-file
